dkube_cicd_controller-1.6.2.dist-info/RECORD
dkube_cicd_controller-1.6.2.dist-info/top_level.txt
dkube_cicd_controller-1.6.2.dist-info/METADATA
dkube_cicd_controller-1.6.2.dist-info/WHEEL
dkube_cicd_controller-1.6.2.dist-info/entry_points.txt
dkube_cicd_controller-1.6.2.dist-info/AUTHORS.rst
dkube_cicd_controller.libs/ld-musl-x86_64-0273b534.so.1
dkube_cicd_controller/dkube_api.cpython-37m-x86_64-linux-gnu.so
dkube_cicd_controller/server.cpython-37m-x86_64-linux-gnu.so
dkube_cicd_controller/sa.cpython-37m-x86_64-linux-gnu.so
dkube_cicd_controller/__init__.cpython-37m-x86_64-linux-gnu.so
dkube_cicd_controller/__init__.py
dkube_cicd_controller/cli.cpython-37m-x86_64-linux-gnu.so
dkube_cicd_controller/utils.cpython-37m-x86_64-linux-gnu.so
dkube_cicd_controller/commands/cicd.cpython-37m-x86_64-linux-gnu.so
dkube_cicd_controller/commands/job.cpython-37m-x86_64-linux-gnu.so
dkube_cicd_controller/commands/image.cpython-37m-x86_64-linux-gnu.so
dkube_cicd_controller/commands/repo.cpython-37m-x86_64-linux-gnu.so
dkube_cicd_controller/commands/build.cpython-37m-x86_64-linux-gnu.so
dkube_cicd_controller/commands/pipeline.cpython-37m-x86_64-linux-gnu.so
dkube_cicd_controller/commands/component.cpython-37m-x86_64-linux-gnu.so
dkube_cicd_controller/commands/__init__.cpython-37m-x86_64-linux-gnu.so
dkube_cicd_controller/commands/__init__.py
dkube_cicd_controller/commands/webhook.cpython-37m-x86_64-linux-gnu.so
dkube_cicd_controller/commands/tekton.cpython-37m-x86_64-linux-gnu.so
dkube_cicd_controller/manifests/triggers.yaml
dkube_cicd_controller/manifests/schema.json
dkube_cicd_controller/manifests/kustomization.yaml
dkube_cicd_controller/manifests/tekton.yaml
dkube_cicd_controller/manifests/dkube-platform-cfg.yaml
dkube_cicd_controller/manifests/tekton-dashboard-release.yaml
dkube_cicd_controller/manifests/interceptors.yaml
dkube_cicd_controller/manifests/kaniko-cache.yaml.j2
dkube_cicd_controller/manifests/tekton-dashboard-vs.yaml
dkube_cicd_controller/manifests/triggers/eventlistener.yaml.j2
dkube_cicd_controller/manifests/triggers/webhook-secret.yaml.j2
dkube_cicd_controller/manifests/triggers/sshrepo.yaml.j2
dkube_cicd_controller/manifests/triggers/role.yaml
dkube_cicd_controller/manifests/triggers/pipeline-template.yaml.j2
