Metadata-Version: 2.1
Name: dkube-cicd-controller
Version: 1.6.2
Summary: CICD controller to automate component building, pipeline deployment to DKube.
Home-page: https://github.com/oneconvergence/dkube_cicd_controller.git
Author: One Convergence
Author-email: dkube@oneconvergence.com
License: UNKNOWN
Keywords: dkube_cicd_controller
Platform: UNKNOWN
Classifier: Development Status :: 2 - Pre-Alpha
Classifier: Intended Audience :: Developers
Classifier: Natural Language :: English
Classifier: Programming Language :: Python :: 3
Classifier: Programming Language :: Python :: 3.5
Classifier: Programming Language :: Python :: 3.6
Classifier: Programming Language :: Python :: 3.7
Classifier: Programming Language :: Python :: 3.8
Requires-Python: >=3.5
Requires-Dist: click (==7.1.2)
Requires-Dist: Jinja2 (==3.0.1)
Requires-Dist: PyYAML (==5.4.1)
Requires-Dist: requests (==2.25.1)
Requires-Dist: boto3 (==1.17.88)
Requires-Dist: logzero (==1.7.0)
Requires-Dist: click-log (==0.3.2)
Requires-Dist: pytest
Requires-Dist: kfp (==1.6.3)
Requires-Dist: GitPython (==3.1.17)
Requires-Dist: Cython (==0.29.23)
Requires-Dist: sentry-sdk (==1.1.0)
Requires-Dist: arrow (==1.1.0)
Requires-Dist: ruamel.yaml (==0.17.7)
Requires-Dist: jsonschema (==3.2.0)
Requires-Dist: giturlparse (==0.10.0)
Requires-Dist: fastapi (==0.65.1)
Requires-Dist: fastapi-utils (==0.2.1)
Requires-Dist: uvicorn (==0.15.0)
Requires-Dist: pytimeparse (==1.1.8)
Requires-Dist: google-api-core (==1.34.0)
Requires-Dist: protobuf (==3.20.3)
